xia_scw_template/__init__.py
xia_scw_template/template.cpython-310-x86_64-linux-gnu.so
xia_scw_template/templates/ScwTemplate/main.tf
xia_scw_template/templates/ScwTemplate/output.tf
xia_scw_template/templates/ScwTemplate/variables.tf
xia_scw_template-0.0.6.dist-info/LICENSE.txt
xia_scw_template-0.0.6.dist-info/METADATA
xia_scw_template-0.0.6.dist-info/WHEEL
xia_scw_template-0.0.6.dist-info/top_level.txt
xia_scw_template-0.0.6.dist-info/RECORD
